[
  {
    "id": "001",
    "title": "PRODUÇÃO MUSICAL",
    "subtitle": "Espaço moderno e qualidade sonora.",
    "image": "/carousel/images/banner01.jpg"
  },
  {
    "id": "002",
    "title": "VENHA NOS CONHECER",
    "subtitle": "Conheça nossos serviços e transforme sua ideia em prática.",
    "image": "/carousel/images/banner02.jpg"
  },
  {
    "id": "003",
    "title": "FÁCIL LOCALIZAÇÃO",
    "subtitle": "A poucos minutos da Av. Paulista.",
    "image": "/carousel/images/banner03.jpg"
  }
]
